isopod/__init__.py
isopod/pipeliner.py
isopod/tracetype.py
isopod-0.0.1a2.dist-info/METADATA
isopod-0.0.1a2.dist-info/WHEEL
isopod-0.0.1a2.dist-info/licenses/LICENSE
isopod-0.0.1a2.dist-info/RECORD
